django_rrweb/__init__.py
django_rrweb/admin.py
django_rrweb/models.py
django_rrweb/urls.py
django_rrweb/views.py
django_rrweb/management/__init__.py
django_rrweb/management/commands/__init__.py
django_rrweb/management/commands/rrwebpurge.py
django_rrweb/migrations/0001_initial.py
django_rrweb/migrations/0002_session_key.py
django_rrweb/migrations/0003_auto_20220818_0457.py
django_rrweb/migrations/0004_auto_20220818_0457.py
django_rrweb/migrations/0005_auto_20220818_2337.py
django_rrweb/migrations/__init__.py
django_rrweb/static/django-rrweb/rrweb-player-0-7-14-style.css
django_rrweb/static/django-rrweb/rrweb-player-0-7-14.js
django_rrweb/static/django-rrweb/rrweb-record-1-1-3.js
django_rrweb/templates/django-rrweb/page-replay.html
django_rrweb/templates/django-rrweb/record-script.js
django_rrweb-4.0.5.dist-info/LICENSE
django_rrweb-4.0.5.dist-info/METADATA
django_rrweb-4.0.5.dist-info/WHEEL
django_rrweb-4.0.5.dist-info/top_level.txt
django_rrweb-4.0.5.dist-info/RECORD
