Metadata-Version: 2.1
Name: django-rrweb
Version: 4.0.5
Summary: Record and replay client web sessions.
Home-page: https://grantjenks.com/docs/django-rrweb/
Author: Grant Jenks
Author-email: contact@grantjenks.com
License: Apache 2.0
Project-URL: Documentation, https://grantjenks.com/docs/django-rrweb/
Project-URL: Source, https://github.com/grantjenks/django-rrweb
Project-URL: Tracker, https://github.com/grantjenks/django-rrweb/issues
Classifier: Development Status :: 5 - Production/Stable
Classifier: Intended Audience :: Developers
Classifier: License :: OSI Approved :: Apache Software License
Classifier: Natural Language :: English
Classifier: Programming Language :: Python
Classifier: Programming Language :: Python :: 3
Classifier: Programming Language :: Python :: Implementation :: CPython
License-File: LICENSE
Requires-Dist: Django
